mixref/__init__.py
mixref/audio/__init__.py
mixref/audio/exceptions.py
mixref/audio/loader.py
mixref/audio/validation.py
mixref/cli/__init__.py
mixref/cli/analyze.py
mixref/cli/main.py
mixref/compare/__init__.py
mixref/detective/__init__.py
mixref/meters/__init__.py
mixref/meters/loudness.py
mixref/meters/targets.py
mixref-0.2.0.dist-info/METADATA
mixref-0.2.0.dist-info/WHEEL
mixref-0.2.0.dist-info/entry_points.txt
mixref-0.2.0.dist-info/licenses/LICENSE
mixref-0.2.0.dist-info/RECORD
