Metadata-Version: 2.4
Name: mixref
Version: 0.2.0
Summary: CLI Audio Analyzer for Music Producers - DnB, Techno, House
Author-email: mixref <dev@mixref.audio>
License: MIT
License-File: LICENSE
Keywords: audio,bpm,dnb,lufs,mastering,music,production,techno
Classifier: Development Status :: 3 - Alpha
Classifier: Intended Audience :: Developers
Classifier: Intended Audience :: End Users/Desktop
Classifier: License :: OSI Approved :: MIT License
Classifier: Operating System :: MacOS
Classifier: Operating System :: Microsoft :: Windows
Classifier: Operating System :: OS Independent
Classifier: Operating System :: POSIX :: Linux
Classifier: Programming Language :: Python :: 3
Classifier: Programming Language :: Python :: 3.12
Classifier: Programming Language :: Python :: 3.13
Classifier: Topic :: Multimedia :: Sound/Audio :: Analysis
Requires-Python: >=3.12
Requires-Dist: librosa>=0.10.0
Requires-Dist: numpy<2.0.0,>=1.26.0
Requires-Dist: pyloudnorm>=0.1.0
Requires-Dist: rich>=13.7.0
Requires-Dist: soundfile>=0.12.0
Requires-Dist: typer>=0.12.0
Provides-Extra: dev
Requires-Dist: mypy>=1.8.0; extra == 'dev'
Requires-Dist: pytest-cov>=4.1.0; extra == 'dev'
Requires-Dist: pytest>=8.0.0; extra == 'dev'
Requires-Dist: ruff>=0.2.0; extra == 'dev'
Requires-Dist: types-setuptools>=69.0.0; extra == 'dev'
Provides-Extra: docs
Requires-Dist: matplotlib>=3.8.0; extra == 'docs'
Requires-Dist: pillow>=10.2.0; extra == 'docs'
Requires-Dist: sphinx-gallery>=0.15.0; extra == 'docs'
Requires-Dist: sphinx-rtd-theme>=2.0.0; extra == 'docs'
Requires-Dist: sphinx>=7.2.0; extra == 'docs'
